{
  "type": "object",
  "allOf": [
    {
      "$ref": "#/components/schemas/MinimalSystemMessage"
    },
    {
      "required": [
        "id"
      ],
      "properties": {
        "attributes": {
          "type": "object",
          "additionalProperties": false,
          "properties": {
            "content": {
              "type": "string",
              "example": "Information regarding shipments"
            },
            "country_code": {
              "oneOf": [
                {
                  "$ref": "#/components/schemas/CountryCode"
                },
                {
                  "type": "null"
                }
              ]
            },
            "level": {
              "type": "string",
              "enum": [
                "info",
                "success",
                "warning",
                "error"
              ],
              "example": "info"
            }
          }
        }
      }
    }
  ]
}
