{
  "type": "object",
  "required": [
    "id",
    "type",
    "attributes",
    "relationships"
  ],
  "properties": {
    "id": {
      "$ref": "../definitions/Uuid.json"
    },
    "type": {
      "type": "string",
      "example": "insurance"
    },
    "attributes": {
      "type": "object",
      "properties": {
        "min": {
          "type": "number",
          "example": "1000"
        },
        "max": {
          "type": "number",
          "example": "2000"
        },
        "price": {
          "type": "number",
          "example": "500"
        },
      }
    }
  }
}
